{
  "baseline": "1_base_naked",
  "benchmark": "math500",
  "n_problems": 100,
  "n_errors": 0,
  "quality": {
    "pass@1": 61.0,
    "final": 61.0
  },
  "system": {
    "avg_tokens_per_problem": 748.8,
    "avg_samples_per_problem": 1.0,
    "avg_latency_s": 14.557,
    "wall_time_s": 257.2,
    "peak_ram_mb": 208.1,
    "peak_vram_mb": 0.0
  },
  "per_problem": [
    {
      "id": "math500-0",
      "pass@1": true,
      "final": true,
      "tokens": 285,
      "latency_s": 6.412,
      "n": 1
    },
    {
      "id": "math500-1",
      "pass@1": false,
      "final": false,
      "tokens": 550,
      "latency_s": 10.8,
      "n": 1
    },
    {
      "id": "math500-2",
      "pass@1": true,
      "final": true,
      "tokens": 483,
      "latency_s": 10.452,
      "n": 1
    },
    {
      "id": "math500-3",
      "pass@1": true,
      "final": true,
      "tokens": 345,
      "latency_s": 8.303,
      "n": 1
    },
    {
      "id": "math500-4",
      "pass@1": true,
      "final": true,
      "tokens": 843,
      "latency_s": 11.608,
      "n": 1
    },
    {
      "id": "math500-5",
      "pass@1": false,
      "final": false,
      "tokens": 205,
      "latency_s": 4.97,
      "n": 1
    },
    {
      "id": "math500-6",
      "pass@1": true,
      "final": true,
      "tokens": 351,
      "latency_s": 8.32,
      "n": 1
    },
    {
      "id": "math500-7",
      "pass@1": false,
      "final": false,
      "tokens": 699,
      "latency_s": 14.46,
      "n": 1
    },
    {
      "id": "math500-8",
      "pass@1": true,
      "final": true,
      "tokens": 294,
      "latency_s": 6.869,
      "n": 1
    },
    {
      "id": "math500-9",
      "pass@1": false,
      "final": false,
      "tokens": 976,
      "latency_s": 18.502,
      "n": 1
    },
    {
      "id": "math500-10",
      "pass@1": false,
      "final": false,
      "tokens": 347,
      "latency_s": 5.429,
      "n": 1
    },
    {
      "id": "math500-11",
      "pass@1": false,
      "final": false,
      "tokens": 528,
      "latency_s": 8.46,
      "n": 1
    },
    {
      "id": "math500-12",
      "pass@1": false,
      "final": false,
      "tokens": 313,
      "latency_s": 3.879,
      "n": 1
    },
    {
      "id": "math500-13",
      "pass@1": true,
      "final": true,
      "tokens": 373,
      "latency_s": 2.942,
      "n": 1
    },
    {
      "id": "math500-14",
      "pass@1": false,
      "final": false,
      "tokens": 275,
      "latency_s": 2.127,
      "n": 1
    },
    {
      "id": "math500-15",
      "pass@1": false,
      "final": false,
      "tokens": 884,
      "latency_s": 13.174,
      "n": 1
    },
    {
      "id": "math500-16",
      "pass@1": true,
      "final": true,
      "tokens": 266,
      "latency_s": 3.889,
      "n": 1
    },
    {
      "id": "math500-17",
      "pass@1": false,
      "final": false,
      "tokens": 453,
      "latency_s": 3.604,
      "n": 1
    },
    {
      "id": "math500-18",
      "pass@1": true,
      "final": true,
      "tokens": 411,
      "latency_s": 4.181,
      "n": 1
    },
    {
      "id": "math500-19",
      "pass@1": true,
      "final": true,
      "tokens": 700,
      "latency_s": 12.207,
      "n": 1
    },
    {
      "id": "math500-20",
      "pass@1": true,
      "final": true,
      "tokens": 167,
      "latency_s": 2.063,
      "n": 1
    },
    {
      "id": "math500-21",
      "pass@1": false,
      "final": false,
      "tokens": 843,
      "latency_s": 15.429,
      "n": 1
    },
    {
      "id": "math500-22",
      "pass@1": false,
      "final": false,
      "tokens": 598,
      "latency_s": 8.555,
      "n": 1
    },
    {
      "id": "math500-23",
      "pass@1": true,
      "final": true,
      "tokens": 488,
      "latency_s": 8.28,
      "n": 1
    },
    {
      "id": "math500-24",
      "pass@1": false,
      "final": false,
      "tokens": 670,
      "latency_s": 10.479,
      "n": 1
    },
    {
      "id": "math500-25",
      "pass@1": false,
      "final": false,
      "tokens": 630,
      "latency_s": 10.135,
      "n": 1
    },
    {
      "id": "math500-26",
      "pass@1": false,
      "final": false,
      "tokens": 348,
      "latency_s": 4.949,
      "n": 1
    },
    {
      "id": "math500-27",
      "pass@1": true,
      "final": true,
      "tokens": 363,
      "latency_s": 4.601,
      "n": 1
    },
    {
      "id": "math500-28",
      "pass@1": true,
      "final": true,
      "tokens": 231,
      "latency_s": 2.912,
      "n": 1
    },
    {
      "id": "math500-29",
      "pass@1": true,
      "final": true,
      "tokens": 359,
      "latency_s": 4.702,
      "n": 1
    },
    {
      "id": "math500-30",
      "pass@1": true,
      "final": true,
      "tokens": 277,
      "latency_s": 4.114,
      "n": 1
    },
    {
      "id": "math500-31",
      "pass@1": true,
      "final": true,
      "tokens": 198,
      "latency_s": 2.777,
      "n": 1
    },
    {
      "id": "math500-32",
      "pass@1": false,
      "final": false,
      "tokens": 255,
      "latency_s": 3.095,
      "n": 1
    },
    {
      "id": "math500-33",
      "pass@1": false,
      "final": false,
      "tokens": 581,
      "latency_s": 9.621,
      "n": 1
    },
    {
      "id": "math500-34",
      "pass@1": true,
      "final": true,
      "tokens": 643,
      "latency_s": 11.194,
      "n": 1
    },
    {
      "id": "math500-35",
      "pass@1": true,
      "final": true,
      "tokens": 351,
      "latency_s": 5.194,
      "n": 1
    },
    {
      "id": "math500-36",
      "pass@1": true,
      "final": true,
      "tokens": 868,
      "latency_s": 15.74,
      "n": 1
    },
    {
      "id": "math500-37",
      "pass@1": true,
      "final": true,
      "tokens": 253,
      "latency_s": 3.393,
      "n": 1
    },
    {
      "id": "math500-38",
      "pass@1": true,
      "final": true,
      "tokens": 229,
      "latency_s": 2.741,
      "n": 1
    },
    {
      "id": "math500-39",
      "pass@1": false,
      "final": false,
      "tokens": 591,
      "latency_s": 10.202,
      "n": 1
    },
    {
      "id": "math500-40",
      "pass@1": true,
      "final": true,
      "tokens": 363,
      "latency_s": 3.981,
      "n": 1
    },
    {
      "id": "math500-41",
      "pass@1": false,
      "final": false,
      "tokens": 8295,
      "latency_s": 190.939,
      "n": 1
    },
    {
      "id": "math500-42",
      "pass@1": true,
      "final": true,
      "tokens": 260,
      "latency_s": 3.366,
      "n": 1
    },
    {
      "id": "math500-43",
      "pass@1": false,
      "final": false,
      "tokens": 641,
      "latency_s": 10.13,
      "n": 1
    },
    {
      "id": "math500-44",
      "pass@1": true,
      "final": true,
      "tokens": 267,
      "latency_s": 2.992,
      "n": 1
    },
    {
      "id": "math500-45",
      "pass@1": true,
      "final": true,
      "tokens": 286,
      "latency_s": 3.945,
      "n": 1
    },
    {
      "id": "math500-46",
      "pass@1": false,
      "final": false,
      "tokens": 501,
      "latency_s": 8.126,
      "n": 1
    },
    {
      "id": "math500-47",
      "pass@1": true,
      "final": true,
      "tokens": 317,
      "latency_s": 4.317,
      "n": 1
    },
    {
      "id": "math500-48",
      "pass@1": false,
      "final": false,
      "tokens": 284,
      "latency_s": 4.28,
      "n": 1
    },
    {
      "id": "math500-49",
      "pass@1": true,
      "final": true,
      "tokens": 302,
      "latency_s": 4.505,
      "n": 1
    },
    {
      "id": "math500-50",
      "pass@1": false,
      "final": false,
      "tokens": 1264,
      "latency_s": 22.98,
      "n": 1
    },
    {
      "id": "math500-51",
      "pass@1": true,
      "final": true,
      "tokens": 888,
      "latency_s": 16.771,
      "n": 1
    },
    {
      "id": "math500-52",
      "pass@1": true,
      "final": true,
      "tokens": 278,
      "latency_s": 3.976,
      "n": 1
    },
    {
      "id": "math500-53",
      "pass@1": true,
      "final": true,
      "tokens": 191,
      "latency_s": 2.287,
      "n": 1
    },
    {
      "id": "math500-54",
      "pass@1": true,
      "final": true,
      "tokens": 146,
      "latency_s": 1.621,
      "n": 1
    },
    {
      "id": "math500-55",
      "pass@1": true,
      "final": true,
      "tokens": 371,
      "latency_s": 5.43,
      "n": 1
    },
    {
      "id": "math500-56",
      "pass@1": true,
      "final": true,
      "tokens": 210,
      "latency_s": 2.663,
      "n": 1
    },
    {
      "id": "math500-57",
      "pass@1": true,
      "final": true,
      "tokens": 330,
      "latency_s": 4.538,
      "n": 1
    },
    {
      "id": "math500-58",
      "pass@1": true,
      "final": true,
      "tokens": 294,
      "latency_s": 4.601,
      "n": 1
    },
    {
      "id": "math500-59",
      "pass@1": true,
      "final": true,
      "tokens": 268,
      "latency_s": 3.357,
      "n": 1
    },
    {
      "id": "math500-60",
      "pass@1": false,
      "final": false,
      "tokens": 708,
      "latency_s": 12.573,
      "n": 1
    },
    {
      "id": "math500-61",
      "pass@1": true,
      "final": true,
      "tokens": 303,
      "latency_s": 3.742,
      "n": 1
    },
    {
      "id": "math500-62",
      "pass@1": false,
      "final": false,
      "tokens": 791,
      "latency_s": 13.594,
      "n": 1
    },
    {
      "id": "math500-63",
      "pass@1": false,
      "final": false,
      "tokens": 820,
      "latency_s": 14.296,
      "n": 1
    },
    {
      "id": "math500-64",
      "pass@1": false,
      "final": false,
      "tokens": 8308,
      "latency_s": 196.496,
      "n": 1
    },
    {
      "id": "math500-65",
      "pass@1": true,
      "final": true,
      "tokens": 137,
      "latency_s": 1.363,
      "n": 1
    },
    {
      "id": "math500-66",
      "pass@1": true,
      "final": true,
      "tokens": 355,
      "latency_s": 5.623,
      "n": 1
    },
    {
      "id": "math500-67",
      "pass@1": true,
      "final": true,
      "tokens": 279,
      "latency_s": 3.725,
      "n": 1
    },
    {
      "id": "math500-68",
      "pass@1": false,
      "final": false,
      "tokens": 619,
      "latency_s": 10.621,
      "n": 1
    },
    {
      "id": "math500-69",
      "pass@1": false,
      "final": false,
      "tokens": 8298,
      "latency_s": 198.08,
      "n": 1
    },
    {
      "id": "math500-70",
      "pass@1": true,
      "final": true,
      "tokens": 319,
      "latency_s": 5.234,
      "n": 1
    },
    {
      "id": "math500-71",
      "pass@1": true,
      "final": true,
      "tokens": 530,
      "latency_s": 9.643,
      "n": 1
    },
    {
      "id": "math500-72",
      "pass@1": true,
      "final": true,
      "tokens": 342,
      "latency_s": 5.479,
      "n": 1
    },
    {
      "id": "math500-73",
      "pass@1": true,
      "final": true,
      "tokens": 313,
      "latency_s": 4.194,
      "n": 1
    },
    {
      "id": "math500-74",
      "pass@1": true,
      "final": true,
      "tokens": 254,
      "latency_s": 3.801,
      "n": 1
    },
    {
      "id": "math500-75",
      "pass@1": true,
      "final": true,
      "tokens": 439,
      "latency_s": 7.439,
      "n": 1
    },
    {
      "id": "math500-76",
      "pass@1": true,
      "final": true,
      "tokens": 300,
      "latency_s": 4.459,
      "n": 1
    },
    {
      "id": "math500-77",
      "pass@1": true,
      "final": true,
      "tokens": 246,
      "latency_s": 3.737,
      "n": 1
    },
    {
      "id": "math500-78",
      "pass@1": false,
      "final": false,
      "tokens": 8312,
      "latency_s": 200.277,
      "n": 1
    },
    {
      "id": "math500-79",
      "pass@1": true,
      "final": true,
      "tokens": 204,
      "latency_s": 2.834,
      "n": 1
    },
    {
      "id": "math500-80",
      "pass@1": false,
      "final": false,
      "tokens": 734,
      "latency_s": 13.906,
      "n": 1
    },
    {
      "id": "math500-81",
      "pass@1": true,
      "final": true,
      "tokens": 408,
      "latency_s": 6.67,
      "n": 1
    },
    {
      "id": "math500-82",
      "pass@1": false,
      "final": false,
      "tokens": 403,
      "latency_s": 5.771,
      "n": 1
    },
    {
      "id": "math500-83",
      "pass@1": false,
      "final": false,
      "tokens": 394,
      "latency_s": 6.99,
      "n": 1
    },
    {
      "id": "math500-84",
      "pass@1": false,
      "final": false,
      "tokens": 374,
      "latency_s": 5.801,
      "n": 1
    },
    {
      "id": "math500-85",
      "pass@1": true,
      "final": true,
      "tokens": 314,
      "latency_s": 4.399,
      "n": 1
    },
    {
      "id": "math500-86",
      "pass@1": true,
      "final": true,
      "tokens": 218,
      "latency_s": 2.812,
      "n": 1
    },
    {
      "id": "math500-87",
      "pass@1": true,
      "final": true,
      "tokens": 349,
      "latency_s": 6.113,
      "n": 1
    },
    {
      "id": "math500-88",
      "pass@1": false,
      "final": false,
      "tokens": 598,
      "latency_s": 10.551,
      "n": 1
    },
    {
      "id": "math500-89",
      "pass@1": true,
      "final": true,
      "tokens": 765,
      "latency_s": 15.627,
      "n": 1
    },
    {
      "id": "math500-90",
      "pass@1": true,
      "final": true,
      "tokens": 170,
      "latency_s": 1.69,
      "n": 1
    },
    {
      "id": "math500-91",
      "pass@1": false,
      "final": false,
      "tokens": 265,
      "latency_s": 3.855,
      "n": 1
    },
    {
      "id": "math500-92",
      "pass@1": true,
      "final": true,
      "tokens": 504,
      "latency_s": 9.34,
      "n": 1
    },
    {
      "id": "math500-93",
      "pass@1": true,
      "final": true,
      "tokens": 405,
      "latency_s": 7.075,
      "n": 1
    },
    {
      "id": "math500-94",
      "pass@1": false,
      "final": false,
      "tokens": 675,
      "latency_s": 5.989,
      "n": 1
    },
    {
      "id": "math500-95",
      "pass@1": true,
      "final": true,
      "tokens": 569,
      "latency_s": 10.398,
      "n": 1
    },
    {
      "id": "math500-96",
      "pass@1": false,
      "final": false,
      "tokens": 744,
      "latency_s": 13.557,
      "n": 1
    },
    {
      "id": "math500-97",
      "pass@1": true,
      "final": true,
      "tokens": 235,
      "latency_s": 3.16,
      "n": 1
    },
    {
      "id": "math500-98",
      "pass@1": true,
      "final": true,
      "tokens": 169,
      "latency_s": 2.282,
      "n": 1
    },
    {
      "id": "math500-99",
      "pass@1": false,
      "final": false,
      "tokens": 429,
      "latency_s": 6.912,
      "n": 1
    }
  ]
}